[
    {
      "constant": true,
      "inputs": [],
      "name": "requestGoal",
      "outputs": [
        {
          "name": "",
          "type": "uint256"
        }
      ],
      "payable": false,
      "stateMutability": "view",
      "type": "function"
    },
    {
      "constant": true,
      "inputs": [],
      "name": "createdBy",
      "outputs": [
        {
          "name": "",
          "type": "uint8"
        }
      ],
      "payable": false,
      "stateMutability": "view",
      "type": "function"
    },
    {
      "constant": true,
      "inputs": [
        {
          "name": "",
          "type": "uint256"
        }
      ],
      "name": "providers",
      "outputs": [
        {
          "name": "",
          "type": "address"
        }
      ],
      "payable": false,
      "stateMutability": "view",
      "type": "function"
    },
    {
      "constant": true,
      "inputs": [],
      "name": "owner",
      "outputs": [
        {
          "name": "",
          "type": "address"
        }
      ],
      "payable": false,
      "stateMutability": "view",
      "type": "function"
    },
    {
      "constant": true,
      "inputs": [],
      "name": "requester",
      "outputs": [
        {
          "name": "",
          "type": "address"
        }
      ],
      "payable": false,
      "stateMutability": "view",
      "type": "function"
    },
    {
      "constant": true,
      "inputs": [],
      "name": "balance",
      "outputs": [
        {
          "name": "",
          "type": "uint256"
        }
      ],
      "payable": false,
      "stateMutability": "view",
      "type": "function"
    },
    {
      "constant": true,
      "inputs": [
        {
          "name": "",
          "type": "address"
        }
      ],
      "name": "mappedProviders",
      "outputs": [
        {
          "name": "",
          "type": "bool"
        }
      ],
      "payable": false,
      "stateMutability": "view",
      "type": "function"
    },
    {
      "constant": true,
      "inputs": [],
      "name": "ownerBalance",
      "outputs": [
        {
          "name": "",
          "type": "uint256"
        }
      ],
      "payable": false,
      "stateMutability": "view",
      "type": "function"
    },
    {
      "constant": true,
      "inputs": [],
      "name": "FEE",
      "outputs": [
        {
          "name": "",
          "type": "uint256"
        }
      ],
      "payable": false,
      "stateMutability": "view",
      "type": "function"
    },
    {
      "constant": true,
      "inputs": [],
      "name": "currentQuantity",
      "outputs": [
        {
          "name": "",
          "type": "uint256"
        }
      ],
      "payable": false,
      "stateMutability": "view",
      "type": "function"
    },
    {
      "constant": true,
      "inputs": [],
      "name": "requestAmount",
      "outputs": [
        {
          "name": "",
          "type": "uint256"
        }
      ],
      "payable": false,
      "stateMutability": "view",
      "type": "function"
    },
    {
      "constant": true,
      "inputs": [],
      "name": "token",
      "outputs": [
        {
          "name": "",
          "type": "address"
        }
      ],
      "payable": false,
      "stateMutability": "view",
      "type": "function"
    },
    {
      "inputs": [
        {
          "name": "_owner",
          "type": "address"
        },
        {
          "name": "_token",
          "type": "address"
        },
        {
          "name": "_requestGoal",
          "type": "uint256"
        }
      ],
      "payable": false,
      "stateMutability": "nonpayable",
      "type": "constructor"
    },
    {
      "anonymous": false,
      "inputs": [
        {
          "indexed": true,
          "name": "provider",
          "type": "address"
        },
        {
          "indexed": false,
          "name": "tokens",
          "type": "uint256"
        }
      ],
      "name": "ProviderAdded",
      "type": "event"
    },
    {
      "anonymous": false,
      "inputs": [
        {
          "indexed": true,
          "name": "provider",
          "type": "address"
        },
        {
          "indexed": false,
          "name": "amount",
          "type": "uint256"
        }
      ],
      "name": "ProviderPaid",
      "type": "event"
    },
    {
      "anonymous": false,
      "inputs": [
        {
          "indexed": false,
          "name": "amount",
          "type": "uint256"
        }
      ],
      "name": "OwnerBalanceWithdrawn",
      "type": "event"
    },
    {
      "anonymous": false,
      "inputs": [
        {
          "indexed": true,
          "name": "buyer",
          "type": "address"
        },
        {
          "indexed": false,
          "name": "amount",
          "type": "uint256"
        }
      ],
      "name": "Buy",
      "type": "event"
    },
    {
      "anonymous": false,
      "inputs": [
        {
          "indexed": true,
          "name": "requester",
          "type": "address"
        },
        {
          "indexed": false,
          "name": "amount",
          "type": "uint256"
        }
      ],
      "name": "Request",
      "type": "event"
    },
    {
      "constant": false,
      "inputs": [
        {
          "name": "fee",
          "type": "uint256"
        }
      ],
      "name": "setFee",
      "outputs": [],
      "payable": false,
      "stateMutability": "nonpayable",
      "type": "function"
    },
    {
      "constant": false,
      "inputs": [
        {
          "name": "provider",
          "type": "address"
        },
        {
          "name": "tokens",
          "type": "uint256"
        }
      ],
      "name": "addProvider",
      "outputs": [],
      "payable": false,
      "stateMutability": "nonpayable",
      "type": "function"
    },
    {
      "constant": true,
      "inputs": [],
      "name": "getProviders",
      "outputs": [
        {
          "name": "",
          "type": "address[]"
        }
      ],
      "payable": false,
      "stateMutability": "view",
      "type": "function"
    },
    {
      "constant": false,
      "inputs": [],
      "name": "buy",
      "outputs": [],
      "payable": true,
      "stateMutability": "payable",
      "type": "function"
    },
    {
      "constant": false,
      "inputs": [],
      "name": "request",
      "outputs": [],
      "payable": true,
      "stateMutability": "payable",
      "type": "function"
    },
    {
      "constant": false,
      "inputs": [],
      "name": "resetBalance",
      "outputs": [],
      "payable": false,
      "stateMutability": "nonpayable",
      "type": "function"
    },
    {
      "constant": false,
      "inputs": [
        {
          "name": "provider",
          "type": "address"
        },
        {
          "name": "providerTokens",
          "type": "uint256"
        }
      ],
      "name": "paid",
      "outputs": [],
      "payable": false,
      "stateMutability": "nonpayable",
      "type": "function"
    },
    {
      "constant": false,
      "inputs": [],
      "name": "withdrawOwnerBalance",
      "outputs": [],
      "payable": false,
      "stateMutability": "nonpayable",
      "type": "function"
    }
  ]
